django_facebook/__init__.py
django_facebook/auth.py
django_facebook/conf.py
django_facebook/decorators.py
django_facebook/middleware.py
django_facebook/signals.py
django_facebook/tasks.py
django_facebook/urls.py
django_facebook/utils.py
django_facebook/views.py
django_facebook/templates/django_facebook/debug.html
django_facebook/templates/tags/facebook_init.html
django_facebook/templates/tags/facebook_load.html
django_facebook/templatetags/__init__.py
django_facebook/templatetags/facebook.py
django_facebook2-0.3.2.dist-info/DESCRIPTION.rst
django_facebook2-0.3.2.dist-info/LICENSE.txt
django_facebook2-0.3.2.dist-info/METADATA
django_facebook2-0.3.2.dist-info/metadata.json
django_facebook2-0.3.2.dist-info/RECORD
django_facebook2-0.3.2.dist-info/top_level.txt
django_facebook2-0.3.2.dist-info/WHEEL
