Metadata-Version: 2.0
Name: django-facebook2
Version: 0.3.2
Summary: Facebook Authentication for Django
Home-page: http://github.com/tino/django-facebook2
Author: Tino de Bruijn
Author-email: tinodb@gmail.com
License: UNKNOWN
Platform: UNKNOWN
Classifier: Development Status :: 4 - Beta
Classifier: Environment :: Web Environment
Classifier: Framework :: Django
Classifier: Intended Audience :: Developers
Classifier: License :: OSI Approved :: MIT License
Classifier: Operating System :: OS Independent
Classifier: Programming Language :: Python
Classifier: Topic :: Software Development :: Libraries :: Python Modules
Requires-Dist: django (>=1.5)
Requires-Dist: facebook2 (>=2.2.1)
